{"name":"Federal University of Santa Maria","alt_name":"Universidade Federal de Santa Maria (UFSM)","country":"Brazil","state":null,"address":{"street":"Avenida Roraima, nº 1000 Cidade Universitária, Bairro Camobi","city":"Santa Maria","province":"Rio Grande do Sul","postal_code":"97105900"},"contact":{"telephone":"+55(55) 3220-8000","website":"http:\/\/www.ufsm.br","email":"gabinete@adm.ufsm.br","fax":"+55(55) 3220-8001"},"funding":"Public","languages":null,"academic_year":"March to December (March-July; August-December)","accrediting_agency":null}
