{"name":"Kuvempu University","alt_name":"Kuvempu Vishwavidyanilaya","country":"India","state":null,"address":{"street":"Jnana Sahyadri, Shimoga Dist.","city":"Shankaraghatta","province":"Karnataka","postal_code":"577451"},"contact":{"telephone":"+91(8282) 256-301 +91(8282) 256-302","website":"http:\/\/www.kuvempu.ac.in","email":"reg_admn@kuvempu.ac.in","fax":"+91(8282) 256-255"},"funding":null,"languages":null,"academic_year":"June to March (June-October; December-March)","accrediting_agency":"National Assessment and Accreditation Council (NAAC)"}
