{"name":"Nirma University","alt_name":null,"country":"India","state":null,"address":{"street":"Sarkhej-Gandhinagar Highway, Post: Chandlodia, Via: Gota","city":"Ahmedabad","province":"Gujarat","postal_code":"382 481"},"contact":{"telephone":"+91 (2717) 241-900  +91 (2717) 241-911","website":"http:\/\/www.nirmauni.ac.in\/","email":"asst_registrar@nirmauni.ac.in","fax":"+91 (2717) 241-916  +91 (2717) 241-917"},"funding":"Private","languages":null,"academic_year":null,"accrediting_agency":"University Grants Commission (UGC)"}
