{"name":"Private University of Santa Cruz de la Sierra","alt_name":"Universidad Privada de Santa Cruz de la Sierra – UPSA (UPSA)","country":"Bolivia","state":null,"address":{"street":"Casilla Postal 2944, Av. Paraguá y 4° anillo, Zona Parque Industrial","city":"Santa Cruz de la Sierra","province":"Andrés Ibañez","postal_code":"2944"},"contact":{"telephone":"+591(3) 346-4000","website":"http:\/\/www.upsa.edu.bo","email":"informaciones@upsa.edu.bo","fax":"+591(3) 346-5757"},"funding":"Private","languages":null,"academic_year":null,"accrediting_agency":null}
