{"name":"Maastricht School of Management","alt_name":"(MSM)","country":"Netherlands","state":null,"address":{"street":"Endepolsdomein 150","city":"Maastricht","province":null,"postal_code":"6229 EP"},"contact":{"telephone":"+31(43) 387-0808","website":"http:\/\/www.msm.nl\/","email":"info@msm.nl","fax":null},"funding":"Private","languages":null,"academic_year":"September to September","accrediting_agency":"Nederlands-Vlaamse Accreditatieorganisatie (NVAO); Association of MBAs (AMBA); The Accreditation Council for Business Schools and Programs (ACBSP); International Assembly for Collegiate Business Education (IACBE)"}
