{"name":"Belarusian-Russian University","alt_name":"Belaruska-Rasijskij Universitet (BRU)","country":"Belarus","state":null,"address":{"street":"Prospect Mira, 43","city":"Mogilev","province":null,"postal_code":"212000"},"contact":{"telephone":"+375(222) 26-61-00","website":"http:\/\/www.bru.by\/","email":"bru@bru.by","fax":"+375(222) 22-58-21"},"funding":"Public","languages":null,"academic_year":"September to June (September-January; February-June)","accrediting_agency":"Ministry of Education; Federal Agency on Education of Ministry of Education and Science of the Russian Federation"}
