{"name":"FPT University","alt_name":"FPT University","country":"Vietnam","state":null,"address":{"street":"Education and Training Park - Hoa Lac Hi-Tech Park - Km29 Thang Long, Thach That, Ho Chi Minh City Hanoi","city":"Hanoi","province":null,"postal_code":null},"contact":{"telephone":"(024) 7300 5588","website":"http://daihoc.fpt.edu.vn/","email":"daihocfpt@fpt.edu.vn","fax":null},"funding":"private","languages":null,"academic_year":"September to July (September-February; February-July)","accrediting_agency":"Ministry of Education and Training"}
