{"name":"Ernst Busch Academy of Dramatic Art","alt_name":"Hochschule für Schauspielkunst 'Ernst Busch' Berlin","country":"Germany","state":null,"address":{"street":"Schnellerstrasse 104","city":"Berlin","province":null,"postal_code":"12439"},"contact":{"telephone":"+49(30) 639975-0","website":"http:\/\/www.hfs-berlin.de","email":"rektorat@hfs-berlin.de","fax":"+49(30) 639975-75"},"funding":"Public","languages":null,"academic_year":"September to August (September-February; February-August)","accrediting_agency":null}
