{"name":"Vietnam National University - Ho Chi Minh City – University of Science","alt_name":"Dai hoc Quôc Gia Tp. Hô Chí Minh – Trường ĐH Khoa học Tự nhiên (UNS)","country":"Vietnam","state":null,"address":{"street":"227 Nguyen Van Cu St.","city":"Hô Chí Minh City","province":null,"postal_code":null},"contact":{"telephone":"+84(8) 835-3193","website":"http:\/\/www.hcmuns.edu.vn","email":null,"fax":"+84(8) 835-0096"},"funding":null,"languages":null,"academic_year":"October to June (October-January; February-June)","accrediting_agency":null}
