{"name":"Estoril Higher Institute for Tourism and Hotel Studies","alt_name":"Escola Superior de Hotelaria e Turismo do Estoril (ESHTE)","country":"Portugal","state":null,"address":{"street":"Avenida Condes de Barcelona, n° 808","city":"Estoril","province":null,"postal_code":"2769-510"},"contact":{"telephone":"+ 351 210 040 725","website":"http:\/\/www.eshte.pt","email":"info@eshte.pt; gab.comunicacao@eshte.pt","fax":"+351(21) 004-0719"},"funding":"Public","languages":null,"academic_year":null,"accrediting_agency":null}
