{"name":"International University of Japan","alt_name":"Kokusai Daigaku (IUJ)","country":"Japan","state":null,"address":{"street":"777 Kokusai-cho","city":"Minami-Uonuma-shi","province":"Niigata","postal_code":"949-7277"},"contact":{"telephone":"+81(25) 779-1104  +81(25) 779-1105","website":"http:\/\/www.iuj.ac.jp","email":"info@iuj.ac.jp; ofcgsir@iuj.ac.jp","fax":"+81(25) 779-1188  +81(25) 779-1187"},"funding":"Private","languages":null,"academic_year":"September to August","accrediting_agency":"Ministry of Education, Culture, Sports, Science and Technology (MEXT)"}
