{"name":"Freiberg University of Mining and Technology","alt_name":"Technische Universität Bergakademie Freiberg – TU Bergakademie Freiber","country":"Germany","state":null,"address":{"street":"Akademiestrasse 6","city":"Freiberg","province":null,"postal_code":"09596"},"contact":{"telephone":"+49(3731) 39-0","website":"http:\/\/www.tu-freiberg.de","email":"postmaster@tu-freiberg.de","fax":"+49(3731) 22195"},"funding":"Public","languages":null,"academic_year":"October to July (October-February; April-July)","accrediting_agency":null}
