{"name":"European Regional Educational Academy","alt_name":"Evropakan Krtakan Taratsashrjanain Akademia – Evropeskaja Regionalnaja Obrazovatelnaja Akademija (EREA)","country":"Armenia","state":null,"address":{"street":"10 Davit Anhaght, Zeitun district","city":"Yerevan","province":null,"postal_code":"0037"},"contact":{"telephone":"+374(10) 246-371","website":"http:\/\/www.eriicta.am","email":"info@era.am","fax":"+374(10) 241-891"},"funding":"Public","languages":null,"academic_year":"September to May","accrediting_agency":"Ministry of Education and Science of Armenia; Armenian National Academy of Science"}
