{"name":"Gh. Asachi Technical University of Iaşi","alt_name":"Universitatea Tehnică Gh. Asachi din Iaşi (UTI)","country":"Romania","state":null,"address":{"street":"b-dul Dimitrie Mangeron, nr. 67","city":"Iaşi","province":null,"postal_code":"700050"},"contact":{"telephone":"+40(232) 27-86-83  +40(232) 27-86-80","website":"http:\/\/www.tuiasi.ro","email":"international@tuiasi.ro","fax":"+40(232) 27-86-28"},"funding":"Public","languages":null,"academic_year":"October to June (October-January; March-June)","accrediting_agency":"Ministry of Education and Research"}
