{"name":"National University of Political Studies and Public Administration","alt_name":"Şcoala Naţională de Studii Politice şi Administrative (SNSPA)","country":"Romania","state":null,"address":{"street":"str. Povernei, nr. 6, Sectorul 1","city":"Bucureşti","province":null,"postal_code":"010643"},"contact":{"telephone":"+40(21) 318-08-97","website":"http:\/\/www.snspa.ro","email":"rectorat@snspa.ro","fax":"+40(21) 312-25-35"},"funding":"Public","languages":null,"academic_year":"October to September","accrediting_agency":"Ministry of Education and Research"}
