{"name":"International Slavic Institute","alt_name":"Meždunarodnyj Slavjanskij Institut (MSI)","country":"Russia","state":null,"address":{"street":"Godovikova str. 9, build. 25","city":"Moskva","province":null,"postal_code":"129085"},"contact":{"telephone":"+7(495) 687-03-39 +7(495) 602-46-76","website":"http:\/\/www.slavinst.ru\/","email":"intslavinst@mtu-net.ru","fax":"+7(495) 687-03-39 +7(495) 602-46-76 +7(495) 602-46-84"},"funding":"Private","languages":null,"academic_year":"September to June","accrediting_agency":"Ministry of Education"}
