{"name":"International Institute for Humanities and Linguistics","alt_name":"Meždunarodnyj Gumanitarno-lingvističeskij Institut (IIHL)","country":"Russia","state":null,"address":{"street":"ul. Bol'šaja Čerjomuškinskaja 17a","city":"Moskva","province":null,"postal_code":"117447"},"contact":{"telephone":"+7(495) 127-2391","website":"http:\/\/www.mgli.ru","email":"mgli@mfua.ru","fax":null},"funding":"Public","languages":null,"academic_year":null,"accrediting_agency":"Russian Ministry of Education (Federal'naja Sluzhba Nadsory v Sfere obrazovanija I Nauki)"}
