{"name":"Krasnojarsk State University of Agriculture","alt_name":"Krasnojarskij Gosudarstvennyj Agrarnyj Universitet (KSAU)","country":"Russia","state":null,"address":{"street":"prosp. Mira 90","city":"Krasnojarsk","province":null,"postal_code":"600049"},"contact":{"telephone":"+7(3912) 273-609","website":"http:\/\/www.kgau.ru","email":"info@kgau.ru","fax":"+7(3912) 273-609"},"funding":"Public","languages":null,"academic_year":"September to July","accrediting_agency":"Ministry of Education and Science"}
