{"name":"Magnitogorsk State University","alt_name":"Magnitogorskij Gosudarstvennyj Universitet","country":"Russia","state":null,"address":{"street":"ul. Lenina 114","city":"Magnitogorsk","province":null,"postal_code":"455043"},"contact":{"telephone":"+7(3511) 351-532  +7(3511) 354-666","website":"http:\/\/www.masu.ru","email":"masu@masu.ru","fax":"+7(3511) 359-232"},"funding":"Public","languages":null,"academic_year":"September to June (September-January; February-June)","accrediting_agency":null}
