{"name":"Russian State Pedagogical University named after Herzen","alt_name":"Rossijskij Gosudarstvennyj Pedagogičeskij Universitet im. A.I. Herzena (HSPU)","country":"Russia","state":null,"address":{"street":"nab. Reki Moiki, 48","city":"Sankt-Peterburg","province":null,"postal_code":"191186"},"contact":{"telephone":"+7(812) 570-08-60","website":"http:\/\/www.herzen.spb.ru","email":"postmaster@herzen.spb.ru","fax":"+7(812) 312-02-22"},"funding":"Public","languages":null,"academic_year":"September to June (September-January; February-June)","accrediting_agency":"Ministry of Education and Science"}
