{"name":"Velikije Luki State Agricultural Academy","alt_name":"Velikolukskaja Gosudarstvennaja Sel'skohozjajstvennaja Akademija (VGSA)","country":"Russia","state":null,"address":{"street":"pl. Lenina 1","city":"Velikje Lukij","province":"Pskovskaja oblast'","postal_code":"182112"},"contact":{"telephone":"+7(81153) 376-71","website":"http:\/\/www.vgsa.ru","email":"vgsha@mart.ru","fax":"+7(81153) 376-71"},"funding":"Public","languages":null,"academic_year":"September to August","accrediting_agency":"Ministry of General and professional Education"}
