{"name":"International Black Sea University","alt_name":"Šavi Zgvis Saertašoriso Universiteti (IBSU)","country":"Georgia","state":null,"address":{"street":"David Agmashenebeli Alley 13km, 2","city":"Tbilisi","province":null,"postal_code":"0131"},"contact":{"telephone":"+995(32) 595-005","website":"http:\/\/www.ibsu.edu.ge","email":"contact@ibsu.edu.ge","fax":"+995(32) 595-008"},"funding":"Private","languages":null,"academic_year":"September to July","accrediting_agency":"Ministry of Education and Science"}
