{"name":"Central American University of Social Sciences","alt_name":"Universidad Centroamericana de Ciencias Sociales (UCACIS)","country":"Costa Rica","state":null,"address":{"street":"Banco Nacional de San Pedro, 2 cuadras al sur, 5 cuadras al este y 4 cuadras al Sur","city":"San José","province":null,"postal_code":null},"contact":{"telephone":"+506 2280-5310","website":"http:\/\/ucacis.ac.cr","email":"info@ucacis.ac.cr","fax":"+506 2280-1607"},"funding":"Private","languages":null,"academic_year":null,"accrediting_agency":"CONESUP"}
