{"name":"National University (Philippines)","alt_name":"(NU)","country":"Philippines","state":null,"address":{"street":"551 Mariano F. Jhocson Street, Sampaloc","city":"Manila","province":"First District, Metro Manila","postal_code":"1008"},"contact":{"telephone":"+63(2) 749-8221","website":"http:\/\/www.national-u.edu.ph","email":"teddyo@nu.edu.ph","fax":"+63(2) 749-8210"},"funding":"Private","languages":null,"academic_year":"June to March (June-October; November-March)","accrediting_agency":null}
