{"name":"San Antonio Abad del Cusco National University","alt_name":"Universidad Nacional de San Antonio Abad del Cusco (UNSAAC)","country":"Peru","state":null,"address":{"street":"Apartado Postal N° 921, Avenida de la Cultura No 733","city":"Cusco","province":null,"postal_code":null},"contact":{"telephone":"+51(84) 232398","website":"http:\/\/www.unsaac.edu.pe","email":"rectorado@unsaac.edu.pe","fax":"+51(84) 222271"},"funding":"Public","languages":null,"academic_year":null,"accrediting_agency":null}
