{"name":"Toribio Rodriguez de Mendoza National University of the Amazon","alt_name":"Universidad Nacional Toribio Rodriguez de Mendoza de Amazonas","country":"Peru","state":null,"address":{"street":"Ciudad Universitaria: El Franco - Barrio de Higos Urco.","city":"Chachapoyas","province":"Amazonas","postal_code":null},"contact":{"telephone":"+51(41) 477955","website":"http:\/\/www.untrm.edu.pe","email":"rectorado@untrm.edu.pe","fax":null},"funding":"Public","languages":null,"academic_year":null,"accrediting_agency":null}
