{"name":"Stockholm University","alt_name":"Stockholms universitet (SU)","country":"Sweden","state":null,"address":{"street":"Universitetsvägen 10 A","city":"Stockholm","province":null,"postal_code":"SE-106 91"},"contact":{"telephone":"+46 (0) 8-16 2000","website":"http:\/\/www.su.se","email":"registrator@su.se; universitetet@su.se","fax":"+46 (0) 8-16 3866"},"funding":"Public","languages":null,"academic_year":"August to June (August-January; January-June)","accrediting_agency":"Swedish Higher Education Authority (UKA)"}
