{"name":"Gaston Berger University of Saint-Louis","alt_name":"Université Gaston Berger de Saint-Louis (UGB)","country":"Senegal","state":null,"address":{"street":"BP 234","city":"Saint-Louis","province":null,"postal_code":null},"contact":{"telephone":"+221 961-23-60  +221 961-23-56","website":"http:\/\/www.ugb.sn","email":"cabinet@ugb.edu.sn","fax":"+221 961-18-84"},"funding":"Public","languages":null,"academic_year":"October to July","accrediting_agency":"Conseil Africain et Malgache pour l’Enseignement Supérieur (CAMES)"}
