{"name":"Higher Institute of Local Development","alt_name":"Institut supérieur de Développement local (ISDL)","country":"Senegal","state":null,"address":{"street":"Liberté V n° 5503, B.P. 16492","city":"Dakar-Fann","province":null,"postal_code":null},"contact":{"telephone":"+221(33) 824-13-11  +221(77) 204-58-38","website":"http:\/\/www.e-isdl.net","email":"isdl_sn@yahoo.fr","fax":null},"funding":"Private","languages":null,"academic_year":null,"accrediting_agency":"Ministère de l’Enseignement Supérieur, des Universités, des Centres Universitaires Régionaux et de la Recherche Scientifique (MESUCURRS)"}
