{"name":"Warsaw University of Technology","alt_name":"Politechnika Warszawska (PW)","country":"Poland","state":null,"address":{"street":"pl. Politechniki 1","city":"Warszawa","province":"mazowieckie","postal_code":"00-661"},"contact":{"telephone":"+48(22) 234-72-11","website":"http:\/\/www.pw.edu.pl","email":"pw@pw.edu.pl","fax":"+48(22) 621-68-92"},"funding":"Public","languages":null,"academic_year":"October to June (October-February; February-June)","accrediting_agency":"Ministry of Science and Higher Education; Polish Accreditation Committee"}
