{"name":"Catholic Salesian Auxilium University Centre","alt_name":"Centro Universitário Católico Salesiano Auxilium (Unisalesiano)","country":"Brazil","state":null,"address":{"street":"Rua Dom Bosco 265","city":"Araçatuba","province":"São Paulo","postal_code":"16400-505"},"contact":{"telephone":"+55(14) 3533-6200","website":"http:\/\/www.unisalesiano.edu.br","email":"academico@unisalesiano.edu.br","fax":null},"funding":"Private","languages":null,"academic_year":null,"accrediting_agency":"Ministry of Education."}
