{"name":"Faculty of Três Pontas","alt_name":"Faculdade de Três Pontas (FATEP)","country":"Brazil","state":null,"address":{"street":"Praça D'Aparecida, 57, Centro","city":"Três Pontas","province":"MG","postal_code":"37190-000"},"contact":{"telephone":"+55(35) 3266-2020","website":"http:\/\/fateps.unis.edu.br","email":"comunicacao@unis.edu.br; p.institucional@unis.edu.br; marcelof@unis.edu.br","fax":"+55(35) 3266-2020"},"funding":"Private","languages":null,"academic_year":null,"accrediting_agency":null}
