{"name":"State University of Santa Cruz","alt_name":"Universidade Estadual de Santa Cruz (UESC)","country":"Brazil","state":null,"address":{"street":"Campus Soane Nazaré de Andrade, Rodovia Jorge Amado, Km 16, Bairro Salobrinho","city":"Ilhéus","province":"Bahia","postal_code":"45662-900"},"contact":{"telephone":"+55(73) 3680-5002","website":"http:\/\/www.uesc.br","email":"reitoria@uesc.br","fax":"+55(73) 3689-1126"},"funding":"Public","languages":null,"academic_year":"March to December","accrediting_agency":null}
