{"name":"United Faculties of the Valley of Araguaia","alt_name":"Faculdades Unidas do Vale do Araguaia","country":"Brazil","state":null,"address":{"street":"Rua Moreira Cabral, 1,000, Domingos Mariano","city":"Barra do Garças","province":"MT","postal_code":"78600-000"},"contact":{"telephone":"+55(65) 3401-1602","website":"http:\/\/www.univar.edu.br","email":"contato@univar.edu.br; univar@univar.edu.br","fax":"+55(65) 3401-1602  +55(65) 3401-1212"},"funding":"Private","languages":null,"academic_year":null,"accrediting_agency":null}
