{"name":"Cranefield College","alt_name":null,"country":"South Africa","state":null,"address":{"street":"PO Box 70591, The Willows","city":"Pretoria","province":"Gauteng","postal_code":"0041"},"contact":{"telephone":"+27(12) 807-3990","website":"http:\/\/www.cranefield.ac.za","email":"info@cranefield.ac.za","fax":"+27(12) 807-5559"},"funding":"Private","languages":null,"academic_year":"January to December","accrediting_agency":"Council on Higher Education; Registered by the Department of Education"}
