{"name":"Stellenbosch University","alt_name":"Stellenbosch University\/Universiteit Stellenbosch","country":"South Africa","state":null,"address":{"street":"Private Bag X1","city":"Matieland","province":null,"postal_code":"7602"},"contact":{"telephone":"+27(21) 808-9111","website":"http:\/\/www.sun.ac.za","email":"info@sun.ac.za; interoff@sun.ac.za","fax":"+27(21) 808-3714"},"funding":"Public","languages":null,"academic_year":"February to December (February-March; April-June; July-September; October-December)","accrediting_agency":"Ministry of Education"}
