{"name":"University of the Visayas","alt_name":"(UV)","country":"Philippines","state":null,"address":{"street":"D. Jakosalem Corner Colon Street","city":"Cebu City","province":"Cebu","postal_code":"6000"},"contact":{"telephone":"+63(32)  416-8226","website":"http:\/\/www.uv.edu.ph\/","email":"registrar@uv.edu.ph","fax":null},"funding":"Private","languages":null,"academic_year":"June to March (June-October; November-March)","accrediting_agency":"Philippine Association of Colleges and Universities - Commission on Accreditation (PACU-COA)"}
