{"name":"Nelson Mandela Metropolitan University","alt_name":"(NMMU)","country":"South Africa","state":null,"address":{"street":"PO Box 77000","city":"Port Elizabeth","province":"Eastern Cape","postal_code":"6031"},"contact":{"telephone":"+27(41) 504-2161","website":"http:\/\/www.nmmu.ac.za","email":"info@nmmu.ac.za; international@nmmu.ac.za","fax":"+27(41) 504-2711"},"funding":"Public","languages":null,"academic_year":"February to November (February-June; July-November)","accrediting_agency":"Higher Education Quality, Committee (HEQC); Umalusi, the Council for Quality Assurance in General and Further Education, and Training"}
