{"name":"University of Coimbra","alt_name":"Universidade de Coimbra (UC)","country":"Portugal","state":null,"address":{"street":"Paço das Escolas","city":"Coimbra","province":null,"postal_code":"3004-531"},"contact":{"telephone":"+351(239) 859-900","website":"http:\/\/www.uc.pt","email":"adm@uc.pt","fax":"+351(239) 827-994"},"funding":"Public","languages":null,"academic_year":"October to July (October-February; March-July)","accrediting_agency":"Ministry of Science, Technology and Higher Education"}
