{"name":"National University of Rosario","alt_name":"Universidad Nacional de Rosario (UNR)","country":"Argentina","state":null,"address":{"street":"Rectorado, Cordoba 1814","city":"Rosario","province":"Santa Fé","postal_code":"S2000AXD"},"contact":{"telephone":"+54(341) 480-2621","website":"http:\/\/www.unr.edu.ar","email":"academica@unr.edu.ar","fax":"+54(341) 480-2621"},"funding":"Public","languages":null,"academic_year":"March to November (March-June; August-November)","accrediting_agency":null}
