{"name":"National University of Santiago del Estero","alt_name":"Universidad Nacional de Santiago del Estero (UNSE)","country":"Argentina","state":null,"address":{"street":"Avenida Belgrano Sur 1912","city":"Santiago del Estero","province":"Santiago del Estero","postal_code":"4200"},"contact":{"telephone":"+54(385) 450-9500","website":"http:\/\/www.unse.edu.ar","email":"info@unse.edu.ar","fax":"+54(385) 450-9544"},"funding":"Public","languages":null,"academic_year":"February to December (March-July; August-December)","accrediting_agency":null}
