{"name":"Technical University of Liberec","alt_name":"Technická univerzita v Liberci (TUL)","country":"Czech Republic","state":null,"address":{"street":"Studentská 1402\/2","city":"Liberec 1","province":null,"postal_code":"461 17"},"contact":{"telephone":"+420 485 351 111","website":"http:\/\/www.tul.cz","email":"info@tul.cz","fax":"+420 485 105 882"},"funding":"Public","languages":null,"academic_year":"September to June (September-January; February-June)","accrediting_agency":"Ministry of Education, Youth and Sports"}
