{"name":"Manhattan Christian College","alt_name":"(MCC)","country":"United States","state":"Kansas","address":{"street":"1415 Anderson Avenue","city":"Manhattan","province":"Kansas","postal_code":"66502-4081"},"contact":{"telephone":"+1(785) 539-3571","website":"http:\/\/www.mccks.edu","email":"admit@mccks.edu; mccweb@mccks.edu","fax":"+1(785) 539-0832"},"funding":"Private","languages":null,"academic_year":null,"accrediting_agency":"North Central Association of Colleges and Schools (NCA); Association for Biblical Higher Education (ABHE)"}
