{"name":"MGH Institute of Health Professions","alt_name":"(MGHIHP)","country":"United States","state":"Massachusetts","address":{"street":"36 First Avenue, Charleston Navy Yard","city":"Boston","province":"Massachusetts","postal_code":"02129"},"contact":{"telephone":"+1(617) 726-3140","website":"http:\/\/www.mghihp.edu","email":"admissions@mghihp.edu","fax":"+1(617) 726-8010"},"funding":"Private","languages":null,"academic_year":"September to August (September-December; January-May; May-August)","accrediting_agency":"New England Association of Schools and Colleges"}
