{"name":"Teachers College of Columbia University","alt_name":null,"country":"United States","state":"New York","address":{"street":"525 West 120th St.","city":"New York","province":"New York","postal_code":"10027"},"contact":{"telephone":"+1(212) 678-3000","website":"http:\/\/www.tc.columbia.edu","email":"tcinfo@tc.columbia.edu","fax":"+1(212) 678-4048"},"funding":"Private","languages":null,"academic_year":"September to May (September-December; January-May). Also Summer Term (May-August)","accrediting_agency":"Middle States Association of Colleges and Schools"}
