{"name":"The University of Texas Health Science Center at Houston","alt_name":"(UT-HOUSTON)","country":"United States","state":"Texas","address":{"street":"PO Box 20036, University Center Tower","city":"Houston","province":"Texas","postal_code":"77225-0036"},"contact":{"telephone":"+1(713) 500-4472","website":"http:\/\/www.uth.tmc.edu","email":null,"fax":"+1(713) 500-3026"},"funding":"Public","languages":null,"academic_year":"September to August","accrediting_agency":"Southern Association of Colleges and Schools. Professonal Accreditation"}
