{"name":"University of Northern Iowa","alt_name":null,"country":"United States","state":"Iowa","address":{"street":"1222 W. 27th Street","city":"Cedar Falls","province":"Iowa","postal_code":"50614-0033"},"contact":{"telephone":"+1(319) 273-2311","website":"http:\/\/www.uni.edu","email":null,"fax":"+1(319) 273-3509"},"funding":"Public","languages":null,"academic_year":"August to May (August-December; January-May)","accrediting_agency":"NCA; North Central Association of Colleges and Universities"}
