{"name":"University of Houston-Victoria","alt_name":"(UHV)","country":"United States","state":"Texas","address":{"street":"3007 N.Ben Wilson","city":"Victoria","province":"Texas","postal_code":"77901-4450"},"contact":{"telephone":"+1(361) 570-4848","website":"http:\/\/www.uhv.edu","email":"landryf@uhv.edu","fax":"+1(361) 570-4334"},"funding":"Public","languages":null,"academic_year":"August to May. Also Summer Session (June-August)","accrediting_agency":"Southern Association of Colleges and Schools"}
