{"name":"University of the Federal District","alt_name":"Universidad del Distrito Federal","country":"Mexico","state":null,"address":{"street":"Cedro No.16, Colonia Santa María la Ribera,, Delegación Cuauhtémoc, Delegación Cuauhtémoc","city":"México","province":"D.F.","postal_code":"06400"},"contact":{"telephone":"+52(55) 36-11-00-30","website":"http:\/\/www.udf.edu.mx","email":"relacionespublicas@udf.edu.mx","fax":null},"funding":"Private","languages":null,"academic_year":null,"accrediting_agency":null}
