{"name":"University of the North (Mexico)","alt_name":"Universidad del Norte, A.C.","country":"Mexico","state":null,"address":{"street":"Venustiano Carranza, 1350, Nte., Centro","city":"Monterrey","province":"Nuevo León","postal_code":"64000"},"contact":{"telephone":"+52(81) 83-48-97-83","website":"http:\/\/www.un.edu.mx","email":"un@un.edu.mx","fax":null},"funding":"Private","languages":null,"academic_year":"January to December (January-April; May-August; September-December)","accrediting_agency":null}
