{"name":"University of Montenegro","alt_name":"Univerzitet Crne Gore","country":"Montenegro","state":null,"address":{"street":"Cetinjska br.2","city":"Podgorica","province":null,"postal_code":"81000"},"contact":{"telephone":"+382(20) 414-255","website":"http:\/\/www.ucg.ac.me\/cg","email":"rektorat@ac.me","fax":"+382(20) 414-230"},"funding":"Public","languages":null,"academic_year":"September to June (September-January; February-June)","accrediting_agency":"Ministarstvo prosvjete i nauke (Ministry of Education and Science)"}
