{"name":"University Corporation of Research and Development","alt_name":"Corporación Universitaria de Investigación y Desarrollo UDI","country":"Colombia","state":null,"address":{"street":"Calle 9 No. 23-55, Barrio la Universidad","city":"Bucaramanga","province":"Santander","postal_code":null},"contact":{"telephone":"+57(7) 632-8811  +57(7) 635-2525","website":"http:\/\/www.udi.edu.co","email":null,"fax":"+57(7) 634-5775"},"funding":"Private","languages":null,"academic_year":null,"accrediting_agency":null}
