{"name":"COMSATS Institute of Information Technology","alt_name":"(CIIT)","country":"Pakistan","state":null,"address":{"street":"Park Road, Chak Shahzad","city":"Islamabad","province":null,"postal_code":"44000"},"contact":{"telephone":"+92(51) 924-7000","website":"http:\/\/www.ciit.edu.pk","email":null,"fax":null},"funding":"Public","languages":null,"academic_year":"September to July (September-January; March-July)","accrediting_agency":"Higher Education Council (HEC); Pakistan Engineering Council (PEC); Pakistan Council of Architects and Town Planners (PCAT-P)"}
