{"name":"Kampala International University Dar es Salaam Constituent College","alt_name":"(KIUDC)","country":"Tanzania","state":null,"address":{"street":"PO Box 9790","city":"Dar es Salaam","province":null,"postal_code":null},"contact":{"telephone":"+256(414) 663-813  +256(414) 26-734  +256(772) 322-563","website":"http:\/\/kiu.ac.tz\/","email":"info@kiu.ac.tz","fax":"+256(414) 501-974"},"funding":"Private","languages":null,"academic_year":null,"accrediting_agency":"Tanzania Commission for Universities (TCU)"}
