{"name":"Andrés Bello University (El Salvador)","alt_name":"Universidad Andrés Bello (UDAB)","country":"El Salvador","state":null,"address":{"street":"1a. Calle Poniente No. 2128, entre 39 y 41 Avenida Norte No 2128, Colonia Flor Blanca","city":"San Salvador","province":null,"postal_code":null},"contact":{"telephone":"+503 2510-7400  +503 2510-7413  +503 2260-8533","website":"http:\/\/unab.edu.sv","email":"informacion@unab.edu.sv","fax":"+503 2260-8541"},"funding":"Private","languages":null,"academic_year":null,"accrediting_agency":null}
