{"name":"Bangun Nusantara Veteran University","alt_name":"Universitas Veteran Bangun Nusantara","country":"Indonesia","state":null,"address":{"street":"Jalan Letjen Sujono Humardani 1, Kampus Jombor","city":"Sukoharjo","province":"Jawa Tengah","postal_code":"57521"},"contact":{"telephone":"+62(271) 593-156","website":"http:\/\/veteranbantara.ac.id\/","email":"info@veteranbantara.ac.id","fax":"+62(271) 591-065"},"funding":"Private","languages":null,"academic_year":null,"accrediting_agency":null}
