{"name":"Benyoucef Benkhedda University of Algiers 1","alt_name":"Université Benyoucef Benkhedda d'Alger 1","country":"Algeria","state":null,"address":{"street":"2, rue Didouche Mourad","city":"Alger","province":null,"postal_code":"16000"},"contact":{"telephone":"+213(21) 63-77-65","website":"http:\/\/www.univ-alger.dz","email":"contact@admin.univ-alger.dz","fax":"+213(21) 64-36-96"},"funding":null,"languages":null,"academic_year":"October to June (October-December; January-April; April-June)","accrediting_agency":"Ministry of Higher Education and Scientific Research"}
