{"name":"Central University of the East","alt_name":"Universidad Central del Este (UCE)","country":"Dominican Republic","state":null,"address":{"street":"Apartado postal 512, Avenida Francisco Alberto Caamaño Deño","city":"San Pedro de Macorís","province":null,"postal_code":null},"contact":{"telephone":"+1 809 520-3562","website":"http:\/\/www.uce.edu.do","email":"info@uce.edu.do","fax":"+1 809 246-2266"},"funding":"Private","languages":null,"academic_year":"January to December (January-April; May-August; September-December)","accrediting_agency":"Secretariado de Estado de Educación Superior, Ciencia y Tecnología"}
