{"name":"Tver State Medical Academy","alt_name":"Tverskaja Gosudarstvennaja Medicinskaja Akademija (TSMA)","country":"Russia","state":null,"address":{"street":"ul. Soveckaja 4","city":"Tver","province":"Tverskaja oblast'","postal_code":"170100"},"contact":{"telephone":"+7(4822) 317-779","website":"http:\/\/www.tvergma.ru\/","email":"info@tvergma.ru","fax":"+7(4822) 345-759"},"funding":"Public","languages":null,"academic_year":"September to June","accrediting_agency":"National Accrediting Agency for Education"}
