{"name":"Centre for the Study of Social Communication","alt_name":"Centro de Estudios de la Comunicación Social","country":"Mexico","state":null,"address":{"street":"Tepic, 43, Col. Roma Sur, Delegación Cuauhtémoc","city":"México","province":"D.F.","postal_code":"06760"},"contact":{"telephone":"+52(5) 55-64-98-43    +52(5) 55-74-33-09","website":null,"email":"cecs1910@prodigy.net.mx","fax":"+52(5) 55-64-79-76"},"funding":"Private","languages":null,"academic_year":null,"accrediting_agency":null}
