{"name":"Centre for Advanced Studies of Hidalgo","alt_name":"Centro Hidalguense de Estudios Superiores, S.C. (CENHIES)","country":"Mexico","state":null,"address":{"street":"Blvd. Luis Donaldo Colosio, 101, Col. Ampliación Santa Julia, Pachuca","city":"San Cayetano","province":"Hidalgo","postal_code":"42080"},"contact":{"telephone":"+52(771) 718-64-74","website":"http:\/\/www.cenhies.edu.mx","email":"contacto@cenhies.edu.mx","fax":null},"funding":"Private","languages":null,"academic_year":null,"accrediting_agency":null}
