{"name":"Higher Technological Institute of Tepeaca","alt_name":"Instituto Tecnológico Superior de Tepeaca","country":"Mexico","state":null,"address":{"street":"Av. Tecnológico S\/N, Ex-Hacienda Santa Ana, San Pablo Actipa","city":"Tepeaca","province":"Puebla","postal_code":"75200"},"contact":{"telephone":"+52(223)  275-14-49","website":"http:\/\/www.itstepeaca.edu.mx","email":"direccion.general@itstepeaca.edu.mx","fax":null},"funding":"Public","languages":null,"academic_year":null,"accrediting_agency":null}
