{"name":"Institute of Higher Studies in Tourism","alt_name":"Instituto de Estudios Superiores de Turismo","country":"Mexico","state":null,"address":{"street":"Privada de Lago No. 38, Col. Américas Unidas, Delegación Benito Juárez","city":"México","province":"D.F.","postal_code":"03610"},"contact":{"telephone":"+52(55) 55-32-32-24","website":"http:\/\/www.iestur.edu.mx","email":"iestur@prodigy.net.mx","fax":null},"funding":"Private","languages":null,"academic_year":null,"accrediting_agency":null}
