{"name":"International University (México)","alt_name":"Universidad Internacional","country":"Mexico","state":null,"address":{"street":"Avenida General Anaya, 313, Col. del Carmen Coyoacán, Delegación Coyoacán","city":"México","province":"D.F.","postal_code":"04100"},"contact":{"telephone":"+52(55) 56-58-64-21","website":"http:\/\/www.internacional.edu.mx","email":"informes@internacional.edu.mx","fax":"+52(55) 56-58-62-46"},"funding":"Private","languages":null,"academic_year":null,"accrediting_agency":null}
