{"name":"Luis Donaldo Colosio Murrieta University Centre","alt_name":"Centro Universitario Luis Donaldo Colosio Murrieta","country":"Mexico","state":null,"address":{"street":"Azucenas 14, Col. Jardines del Sur, Centro","city":"Huajuapán de León","province":"Oaxaca","postal_code":"69000"},"contact":{"telephone":"+52(953) 532-25-77","website":"http:\/\/cucolosio.edu.mx","email":"dirgral@cucolosio.edu.mx","fax":null},"funding":"Private","languages":null,"academic_year":null,"accrediting_agency":null}
