{"name":"Mexican Association of Psychoanalytic Psychotherapy for Children and Adolescents","alt_name":"Asociación Mexicana de Psicoterapia Psicoanalítica para Infancia y Adolescentes","country":"Mexico","state":null,"address":{"street":"Patriotismo N° 8 Piso 12, Col. Hipódromo Condesa","city":"México","province":"D.F.","postal_code":"06100"},"contact":{"telephone":"+52(555) 516-51-58","website":null,"email":null,"fax":null},"funding":"Private","languages":null,"academic_year":null,"accrediting_agency":null}
