{"name":"Technological Institute of Tlalpan","alt_name":"Instituto Tecnológico de Tlalpan","country":"Mexico","state":null,"address":{"street":"Cerrada de Santa Cruz 4, Predio Tetenco, Col. Centro Pueblo de San Miguel Topilejo,, Delegación Tlalpan, México, D.F.","city":"Ciudad de México","province":"D.F.","postal_code":"14500"},"contact":{"telephone":"+52(55) 5513- 5151","website":"http:\/\/www.ittlalpan.edu.mx","email":"dir_tlalpan@tecnm.mx.","fax":null},"funding":"Public","languages":null,"academic_year":null,"accrediting_agency":null}
