{"name":"Technological University of Tlaxcala","alt_name":"Universidad Tecnológica de Tlaxcala","country":"Mexico","state":null,"address":{"street":"Carretera a el Carmen Xalpatlahuaya s\/n, Francisco I. Madero, 304, Fracc. El Calvario","city":"Huamantla","province":"Tlaxcala","postal_code":"90500"},"contact":{"telephone":"+52(247) 472-53-00","website":"http:\/\/www.uttlaxcala.edu.mx","email":"omondragon@uttlaxcala.edu.mx","fax":null},"funding":"Public","languages":null,"academic_year":null,"accrediting_agency":null}
