{"name":"Andijan State Medical Institute","alt_name":"Andijon Davlat Tibbiyot Instituti – Andizjanskij Meditsinskij Institut (ASMI)","country":"Uzbekistan","state":null,"address":{"street":"Yu.Otabekov ko‘chasi, 1-uy","city":"Andijan","province":null,"postal_code":"170015"},"contact":{"telephone":"+998(74) 237-55-06","website":"http:\/\/www.adti.uz\/","email":"info@adti; uz","fax":"+998(74) 237-54-33"},"funding":"Public","languages":null,"academic_year":null,"accrediting_agency":"Ministry of Higher and Secondary Specialized Education"}
