{"name":"Illinois State University","alt_name":null,"country":"United States","state":"Illinois","address":{"street":"1000 Illinois State University","city":"Normal","province":"Illinois","postal_code":"61790-1000"},"contact":{"telephone":"+1(309) 438-2111","website":"http:\/\/www.ilstu.edu","email":null,"fax":"+1(309) 438-2768"},"funding":"Public","languages":null,"academic_year":"August to May. Also Summer Session (May-August)","accrediting_agency":"North Central Association of Colleges and Schools"}
