{"name":"Mount Carmel College of Nursing","alt_name":null,"country":"United States","state":"Ohio","address":{"street":"127 S. Davis Avenue","city":"Columbus","province":"Ohio","postal_code":"43222-1504"},"contact":{"telephone":"+1(614) 225-5800","website":"http:\/\/www.mccn.edu","email":null,"fax":"+1(614) 234-2875"},"funding":"Private","languages":null,"academic_year":"August to May (August-December; January-May). Summer session: May-August","accrediting_agency":"North Central Association of College and Schools"}
