{"name":"Mount Saint Mary's University","alt_name":null,"country":"United States","state":"Maryland","address":{"street":"16300 Old Emmitsburg Road","city":"Emmitsburg","province":"Maryland","postal_code":"21727"},"contact":{"telephone":"+1(301) 447-6122","website":"http:\/\/www.msmary.edu","email":"admissions@msmary.edu","fax":"+1(301) 447-5755"},"funding":"Private","languages":null,"academic_year":"August to May (August-January; January-May). Also Summer Session (May-August)","accrediting_agency":"Middle States Commission on Higher Education (MSCHE); National Council for Accreditation of Teacher Education (NCATE); International Assembly for Collegiate Business Education (IACBE)"}
