{"name":"Shippensburg University of Pennsylvania","alt_name":null,"country":"United States","state":"Pennsylvania","address":{"street":"1871 Old Main Drive","city":"Shippensburg","province":"Pennsylvania","postal_code":"17257-2299"},"contact":{"telephone":"+1(717) 477-7447","website":"http:\/\/www.ship.edu","email":"wnruud@ship.edu","fax":"+1(717) 477-1273"},"funding":"Public","languages":null,"academic_year":"August to May (August-December; January-May)","accrediting_agency":"Middle States Commission on Higher Education, the AACSB International; National Council for the Accreditation of Teacher Education, AACSB International, ABET, Inc., Accrediting Council on Education in Journalism and Mass Communication (ACEJMC), American Chemical Society, Council on Social Work Education, Council for the Accreditation of Counseling and Related Educational Programs, International Association of Counseling Services, National Council for the Accreditation of Teachers, and Council for Exceptional Children"}
