{"name":"The Baptist College of Florida","alt_name":null,"country":"United States","state":"Florida","address":{"street":"5400 College Dr.","city":"Graceville","province":"Florida","postal_code":"32440-1831"},"contact":{"telephone":"+1(850) 263-3261","website":"http:\/\/www.baptistcollege.edu\/","email":"admissions@baptistcollege.edu","fax":"+1(850) 263-9026"},"funding":"Private","languages":null,"academic_year":null,"accrediting_agency":"Commission on Colleges of the Southern Association of College and Schools"}
