{"name":"The Sage Colleges – Sage College of Albany","alt_name":null,"country":"United States","state":"New York","address":{"street":"140 New Scotland Ave.","city":"Albany","province":"New York","postal_code":"12208"},"contact":{"telephone":"+1(518) 244-2000","website":"http:\/\/www.sage.edu\/SCA","email":"scaadm@sage.edu","fax":"+1(518) 292-1728"},"funding":"Private","languages":null,"academic_year":null,"accrediting_agency":"Middle States Association of Colleges and Schools, Commission on Higher Education"}
