{"name":"University of Maryland Baltimore County","alt_name":"(UMBC)","country":"United States","state":"Maryland","address":{"street":"1000 Hilltop Circle","city":"Baltimore","province":"Maryland","postal_code":"21250-5394"},"contact":{"telephone":"+1(410) 455-1000","website":"http:\/\/www.umbc.edu","email":"homepage@umbc.edu","fax":"+1(410) 455-1210"},"funding":"Public","languages":null,"academic_year":"September to May (September-December; January-May)","accrediting_agency":"Middle States Commission on Higher Education"}
