{"name":"University of Wisconsin-Stout","alt_name":"(UW-Stout)","country":"United States","state":"Wisconsin","address":{"street":"15 Administration Building","city":"Menomonie","province":"Wisconsin","postal_code":"54751"},"contact":{"telephone":"+1(715) 232-1122","website":"http:\/\/www.uwstout.edu","email":"admissions@uwstout.edu","fax":"+1(715) 232-1667"},"funding":"Public","languages":null,"academic_year":"August to May (August-December; January-May)","accrediting_agency":"North-Central Association of Colleges and Schools"}
