{"name":"Weber State University","alt_name":"(WSU)","country":"United States","state":"Utah","address":{"street":"1001 University Circle","city":"Ogden","province":"Utah","postal_code":"84408-1001"},"contact":{"telephone":"+1(801) 626-6000","website":"http:\/\/www.weber.edu","email":"admissions@weber.edu","fax":"+1(801) 626-7922"},"funding":"Public","languages":null,"academic_year":"September to June (September-December; January-March; March-June). Also Summer Session (June-August)","accrediting_agency":"Northwest Association of Schools and Colleges"}
