{"name":"Willamette University","alt_name":null,"country":"United States","state":"Oregon","address":{"street":"900 State Street","city":"Salem","province":"Oregon","postal_code":"97301"},"contact":{"telephone":"+1(503) 370-6300","website":"http:\/\/www.willamette.edu","email":"registrar@willamette.edu","fax":"+1(503) 370-6148"},"funding":"Private","languages":null,"academic_year":"August to May (August-December; January-May)","accrediting_agency":"Northwest Commission on Colleges and Universities"}
