{"name":"Mikkeli University of Applied Sciences","alt_name":"Mikkelin ammattikorkeakoulu (Mamk)","country":"Finland","state":null,"address":{"street":"Patteristonkatu 1 H","city":"Mikkeli","province":null,"postal_code":"50101"},"contact":{"telephone":"+358(15) 355-61","website":"http:\/\/www.mamk.fi","email":"mamk@mamk.fi","fax":"+358(15) 355-6464"},"funding":"Public","languages":null,"academic_year":"First year students: from last week of August to mid May., Other students: from first week of September to mid May., International summer term on selected topics.","accrediting_agency":"Ministry of Education and Culture"}
