{"name":"Kurt Bösch University Institute","alt_name":"Institut Universitaire Kurt Bösch (IUKB)","country":"Switzerland","state":null,"address":{"street":"Case postale 4176","city":"Sion","province":"4","postal_code":"1950"},"contact":{"telephone":"+41(27) 205-73-00","website":"http:\/\/www.iukb.ch","email":"institut@iukb.ch","fax":"+41(27) 205-73-01"},"funding":"Public","languages":null,"academic_year":"August to July (August-January; February-July)","accrediting_agency":"Swiss University Conference"}
