{"name":"University of Lausanne","alt_name":"Université de Lausanne (UNIL)","country":"Switzerland","state":null,"address":{"street":"Unicentre","city":"Lausanne","province":null,"postal_code":"1015"},"contact":{"telephone":"+41(21) 692-11-11","website":"http:\/\/www.unil.ch","email":"acw@unil.ch","fax":"+41(21) 692-26-15"},"funding":"Public","languages":null,"academic_year":"September to July (autumn semester: September-February; spring semester: February-July)","accrediting_agency":"Swiss Center of Accreditation and Quality Assurance in Higher Education (OAQ), EQUIS"}
