{"name":"Institute of Teacher Training and Educational Science Mataram","alt_name":"Institut Keguruan dan Ilmu Pendidikan (IKIP) Mataram (IKIP)","country":"Indonesia","state":null,"address":{"street":"Jalan Pemuda 59 A","city":"Mataram","province":"Nusa Tenggara Barat","postal_code":"83126"},"contact":{"telephone":"+62(370) 632-082","website":"http:\/\/ikipmataram.ac.id","email":"puscom.ikipmataram@gmail.com","fax":"+62(370) 632-082"},"funding":"Private","languages":null,"academic_year":"September to June (September-January; February-June)","accrediting_agency":"Ministry of National Education"}
