{"name":"Serambi Mekkah University","alt_name":"Universitas Serambi Mekkah (USM)","country":"Indonesia","state":null,"address":{"street":"Jalan Tengku Imam Leung Bata Bathoh","city":"Banda Aceh","province":"Nangroeh Aceh Darussalam","postal_code":"23249"},"contact":{"telephone":"+ 62(651) 26-160","website":"http:\/\/www.serambimekkah.ac.id\/","email":null,"fax":"+ 62(651) 22-471"},"funding":"Private","languages":null,"academic_year":null,"accrediting_agency":"National Accreditation Board (BAN-PT)"}
