{"name":"Jan Matejko Academy of Fine Arts in Kraków","alt_name":"Akademia Sztuk Pięknych im. Jana Matejki w Krakowie (ASP)","country":"Poland","state":null,"address":{"street":"pl. Jana Matejki 13","city":"Kraków","province":"małopolskie","postal_code":"31-157"},"contact":{"telephone":"+48(12) 299-20-00","website":"http:\/\/www.asp.krakow.pl","email":"rektor@asp.krakow.pl","fax":"+48(12) 422-65-66"},"funding":"Public","languages":null,"academic_year":"October to June (October-February; February-June)","accrediting_agency":"Ministry of Science and Higher Education; Polish Accreditation Committee"}
